code2clipboard/__init__.py
code2clipboard/code2clipboard.py
code2clipboard-0.1.3.dist-info/LICENSE.md
code2clipboard-0.1.3.dist-info/METADATA
code2clipboard-0.1.3.dist-info/WHEEL
code2clipboard-0.1.3.dist-info/entry_points.txt
code2clipboard-0.1.3.dist-info/top_level.txt
code2clipboard-0.1.3.dist-info/RECORD
