Metadata-Version: 2.1
Name: code2clipboard
Version: 0.1.3
Summary: A utility that scans any codebase and generates prompts directly to your clipboard, ready to be pasted into your preferred AI assistant.
Author-email: Domguia Joseph <domguiajm@gmail.com>
Project-URL: Source, https://github.com/domguia/code2clipboard
Project-URL: Tracker, https://github.com/domguia/code2clipboard/issues
Keywords: tree,tokens,clipboard,pyperclip
Classifier: Programming Language :: Python :: 3
Classifier: License :: OSI Approved :: MIT License
Classifier: Operating System :: OS Independent
Requires-Python: >=3.7
License-File: LICENSE.md
Requires-Dist: pathspec
Requires-Dist: pyperclip
Requires-Dist: tiktoken
Provides-Extra: dev
Requires-Dist: build; extra == "dev"
Requires-Dist: bump2version; extra == "dev"
Requires-Dist: twine; extra == "dev"
